{
  "annotations": {
    "changelogDate": "20251119223624"
  },
  "applications": "*",
  "documentation": "Ítems de la factura",
  "fields": [
    {
      "fieldName": "cantidad",
      "fieldType": "Integer",
      "fieldValidateRules": ["required"]
    },
    {
      "fieldName": "precioUnitario",
      "fieldType": "BigDecimal",
      "fieldValidateRules": ["required"]
    },
    {
      "fieldName": "subtotal",
      "fieldType": "BigDecimal",
      "fieldValidateRules": ["required"]
    }
  ],
  "name": "DetalleFactura",
  "pagination": "infinite-scroll",
  "relationships": [
    {
      "otherEntityField": "nombre",
      "otherEntityName": "producto",
      "relationshipName": "producto",
      "relationshipSide": "left",
      "relationshipType": "many-to-one"
    },
    {
      "otherEntityName": "factura",
      "otherEntityRelationshipName": "detalles",
      "relationshipName": "factura",
      "relationshipSide": "right",
      "relationshipType": "many-to-one"
    }
  ],
  "searchEngine": "no",
  "service": "serviceImpl"
}
